README.rst
setup.py
oldclient/__init__.py
oldclient/models.py
oldclient/oldclient.py
oldclient.egg-info/PKG-INFO
oldclient.egg-info/SOURCES.txt
oldclient.egg-info/dependency_links.txt
oldclient.egg-info/requires.txt
oldclient.egg-info/top_level.txt