Metadata-Version: 1.1
Name: oldclient
Version: 0.0.1
Summary: A Python module for making HTTP requests to Online Linguistic Database (OLD) instances.
Home-page: http://www.onlinelinguisticdatabase.org/
Author: Joel Dunham
Author-email: UNKNOWN
License: Apache License 2.0
Platform: UNKNOWN
Classifier: Environment :: Console
Classifier: Intended Audience :: Developers
Classifier: Operating System :: OS Independent
Classifier: Programming Language :: Python
Classifier: Programming Language :: Python :: 3.6
Classifier: Programming Language :: Python :: 3.7
